{
  "solver": "SAT",
  "model": "base",
  "data_file": "ins-12",
  "search": "linear",
  "symmetry": false,
  "cumulative": true,
  "TOTAL_TIME": 3.0798022747039795,
  "stats": {
    "conflicts": 14061,
    "decisions": 465989,
    "propagations": 10043754,
    "binary propagations": 3359059,
    "restarts": 91,
    "final checks": 1,
    "mk clause": 54952,
    "mk clause binary": 14418,
    "del clause": 3967,
    "minimized lits": 79476,
    "num checks": 1,
    "mk bool var": 15821,
    "arith-make-feasible": 2,
    "arith-max-columns": 4,
    "num allocs": 7369744,
    "rlimit count": 14175419,
    "max memory": 44.24,
    "memory": 43.39,
    "time": 1.434
  },
  "solution": {
    "width": 19,
    "n_circuits": 14,
    "widths": [
      3,
      3,
      3,
      3,
      3,
      3,
      3,
      3,
      3,
      3,
      3,
      4,
      4,
      4
    ],
    "heights": [
      3,
      4,
      5,
      6,
      7,
      8,
      9,
      10,
      11,
      13,
      19,
      5,
      6,
      8
    ],
    "x": [
      0,
      6,
      6,
      3,
      0,
      13,
      0,
      6,
      13,
      3,
      16,
      9,
      9,
      9
    ],
    "y": [
      7,
      15,
      0,
      0,
      0,
      0,
      10,
      5,
      8,
      6,
      0,
      14,
      0,
      6
    ],
    "min_makespan": 19,
    "max_makespan": 33,
    "makespan": 19
  }
}