{
  "solver": "SAT",
  "model": "rotation",
  "data_file": "ins-4",
  "search": "binary",
  "symmetry": false,
  "cumulative": true,
  "TOTAL_TIME": 0.5505974292755127,
  "stats": {
    "conflicts": 602,
    "decisions": 39919,
    "propagations": 427237,
    "binary propagations": 138290,
    "restarts": 5,
    "final checks": 1,
    "mk clause": 19637,
    "del clause": 176,
    "minimized lits": 751,
    "num checks": 1,
    "mk bool var": 7175,
    "arith-make-feasible": 2,
    "arith-max-columns": 4,
    "num allocs": 2432250,
    "rlimit count": 939305,
    "max memory": 25.97,
    "memory": 25.97,
    "time": 0.104
  },
  "solution": {
    "width": 11,
    "n_circuits": 7,
    "widths": [
      3,
      3,
      3,
      6,
      5,
      5,
      8
    ],
    "heights": [
      3,
      4,
      5,
      3,
      3,
      4,
      4
    ],
    "x": [
      8,
      5,
      8,
      0,
      6,
      0,
      0
    ],
    "y": [
      0,
      4,
      3,
      8,
      8,
      4,
      0
    ],
    "min_makespan": 11,
    "max_makespan": 13,
    "makespan": 11
  }
}