{
  "solver": "SAT",
  "model": "base",
  "data_file": "ins-33",
  "search": "binary",
  "symmetry": true,
  "cumulative": false,
  "TOTAL_TIME": 205.01343870162964,
  "stats": {
    "conflicts": 2054464,
    "decisions": 8961668,
    "propagations": 1833490125,
    "binary propagations": 890793159,
    "restarts": 1588,
    "final checks": 1,
    "mk clause": 2104890,
    "mk clause binary": 35454,
    "del clause": 2023360,
    "minimized lits": 41153093,
    "num checks": 1,
    "mk bool var": 26244,
    "arith-make-feasible": 2,
    "arith-max-columns": 4,
    "num allocs": 1212906818,
    "rlimit count": 1781262981,
    "max memory": 63.47,
    "memory": 63.17,
    "time": 204.729
  },
  "solution": {
    "width": 40,
    "n_circuits": 20,
    "widths": [
      3,
      3,
      3,
      3,
      3,
      3,
      3,
      3,
      3,
      3,
      3,
      4,
      4,
      4,
      5,
      5,
      5,
      5,
      5,
      22
    ],
    "heights": [
      3,
      4,
      5,
      6,
      7,
      8,
      9,
      10,
      12,
      16,
      40,
      4,
      14,
      22,
      3,
      4,
      8,
      12,
      13,
      40
    ],
    "x": [
      0,
      30,
      30,
      0,
      0,
      0,
      30,
      30,
      30,
      0,
      33,
      36,
      36,
      36,
      25,
      25,
      25,
      25,
      25,
      3
    ],
    "y": [
      6,
      19,
      35,
      0,
      9,
      16,
      10,
      0,
      23,
      24,
      0,
      0,
      26,
      4,
      29,
      25,
      32,
      13,
      0,
      0
    ],
    "min_makespan": 40,
    "max_makespan": 76,
    "makespan": 40
  }
}