{
  "solver": "SMT",
  "model": "rotation",
  "data_file": "ins-36",
  "search": "linear",
  "symmetry": false,
  "cumulative": true,
  "TOTAL_TIME": 115.82285904884338,
  "stats": [],
  "solution": {
    "width": 15,
    "n_circuits": 25,
    "widths": [
      7,
      7,
      1,
      1,
      3,
      2,
      2,
      2,
      3,
      1,
      6,
      6,
      2,
      2,
      3,
      4,
      1,
      3,
      3,
      2,
      5,
      3,
      3,
      3,
      3
    ],
    "heights": [
      12,
      7,
      7,
      5,
      2,
      6,
      7,
      5,
      1,
      6,
      12,
      9,
      12,
      7,
      10,
      1,
      5,
      16,
      5,
      4,
      2,
      10,
      9,
      16,
      5
    ],
    "x": [
      3,
      6,
      0,
      0,
      12,
      1,
      10,
      4,
      1,
      0,
      9,
      9,
      13,
      4,
      6,
      0,
      0,
      1,
      12,
      4,
      4,
      3,
      6,
      0,
      10
    ],
    "y": [
      28,
      21,
      10,
      5,
      38,
      34,
      33,
      13,
      16,
      34,
      9,
      0,
      21,
      2,
      11,
      17,
      0,
      0,
      33,
      9,
      0,
      18,
      2,
      18,
      28
    ],
    "min_makespan": 40,
    "max_makespan": 53,
    "makespan": 40
  }
}