{
  "solution": {
    "width": 21,
    "n_circuits": 15,
    "widths": [
      3.0,
      3.0,
      5.0,
      3.0,
      3.0,
      8.0,
      3.0,
      3.0,
      3.0,
      3.0,
      4.0,
      4.0,
      4.0,
      6.0,
      5.0
    ],
    "heights": [
      3.0,
      4.0,
      3.0,
      6.0,
      7.0,
      3.0,
      9.0,
      10.0,
      14.0,
      18.0,
      4.0,
      6.0,
      11.0,
      5.0,
      15.0
    ],
    "x": [
      18.0,
      5.0,
      0,
      15.0,
      12.0,
      0,
      12.0,
      15.0,
      5.0,
      18.0,
      8.0,
      8.0,
      8.0,
      12.0,
      0
    ],
    "y": [
      18.0,
      0,
      15.0,
      0,
      0,
      18.0,
      7.0,
      6.0,
      4.0,
      0,
      11.0,
      15.0,
      0,
      16.0,
      0
    ],
    "min_makespan": 21,
    "max_makespan": 33,
    "makespan": 21.0
  },
  "stats": [],
  "model": "rotation",
  "data_file": "ins-14",
  "solver": "z3 SAT",
  "TOTAL_TIME": 38.86842393875122
}