{
  "solver": "SMT",
  "model": "rotation",
  "data_file": "ins-1",
  "search": "linear",
  "symmetry": true,
  "cumulative": true,
  "TOTAL_TIME": 0.0029020309448242188,
  "stats": [],
  "solution": {
    "width": 8,
    "n_circuits": 4,
    "widths": [
      3,
      3,
      5,
      5
    ],
    "heights": [
      3,
      5,
      3,
      5
    ],
    "x": [
      0,
      0,
      3,
      3
    ],
    "y": [
      0,
      3,
      5,
      0
    ],
    "min_makespan": 8,
    "max_makespan": 8,
    "makespan": 8
  }
}