{
  "solver": "SAT",
  "model": "base",
  "data_file": "ins-36",
  "search": "linear",
  "symmetry": true,
  "cumulative": false,
  "TOTAL_TIME": 49.24782347679138,
  "stats": {
    "conflicts": 452790,
    "decisions": 8029984,
    "propagations": 363776706,
    "binary propagations": 183547692,
    "restarts": 849,
    "final checks": 1,
    "mk clause": 521511,
    "mk clause binary": 51231,
    "del clause": 417132,
    "minimized lits": 7906252,
    "num checks": 1,
    "mk bool var": 36693,
    "arith-make-feasible": 2,
    "arith-max-columns": 4,
    "num allocs": 240358322,
    "rlimit count": 414250968,
    "max memory": 81.07,
    "memory": 80.66,
    "time": 48.865
  },
  "solution": {
    "width": 15,
    "n_circuits": 25,
    "widths": [
      7,
      7,
      1,
      1,
      2,
      2,
      2,
      2,
      1,
      1,
      6,
      6,
      2,
      2,
      3,
      1,
      1,
      3,
      3,
      2,
      2,
      3,
      3,
      3,
      3
    ],
    "heights": [
      12,
      7,
      7,
      5,
      3,
      6,
      7,
      5,
      3,
      6,
      12,
      9,
      12,
      7,
      10,
      4,
      5,
      16,
      5,
      4,
      5,
      10,
      9,
      16,
      5
    ],
    "x": [
      2,
      5,
      11,
      14,
      3,
      13,
      0,
      9,
      2,
      12,
      5,
      3,
      0,
      0,
      11,
      14,
      14,
      9,
      12,
      12,
      0,
      12,
      0,
      2,
      12
    ],
    "y": [
      9,
      33,
      26,
      16,
      37,
      0,
      28,
      16,
      37,
      0,
      21,
      0,
      9,
      21,
      16,
      36,
      21,
      0,
      31,
      36,
      35,
      6,
      0,
      21,
      26
    ],
    "min_makespan": 40,
    "max_makespan": 53,
    "makespan": 40
  }
}