{
  "solver": "SAT",
  "model": "rotation",
  "data_file": "ins-9",
  "search": "binary",
  "symmetry": true,
  "cumulative": false,
  "TOTAL_TIME": 0.8685441017150879,
  "stats": {
    "conflicts": 16009,
    "decisions": 107767,
    "propagations": 4677637,
    "binary propagations": 2101401,
    "restarts": 102,
    "final checks": 1,
    "mk clause": 27971,
    "del clause": 10988,
    "minimized lits": 111465,
    "num checks": 1,
    "mk bool var": 6265,
    "arith-make-feasible": 2,
    "arith-max-columns": 4,
    "num allocs": 2373244,
    "rlimit count": 5522026,
    "max memory": 25.43,
    "memory": 25.33,
    "time": 0.753
  },
  "solution": {
    "width": 16,
    "n_circuits": 10,
    "widths": [
      3,
      4,
      5,
      6,
      3,
      8,
      10,
      12,
      4,
      9
    ],
    "heights": [
      3,
      3,
      3,
      3,
      7,
      3,
      3,
      3,
      7,
      7
    ],
    "x": [
      0,
      12,
      11,
      0,
      13,
      3,
      6,
      0,
      0,
      4
    ],
    "y": [
      0,
      10,
      0,
      13,
      3,
      0,
      13,
      10,
      3,
      3
    ],
    "min_makespan": 16,
    "max_makespan": 25,
    "makespan": 16
  }
}